vagents/__init__.py
vagents/contrib/impl/__init__.py
vagents/contrib/impl/libsql_vdb.py
vagents/core/__init__.py
vagents/core/encoder.py
vagents/core/executor.py
vagents/core/model.py
vagents/core/module.py
vagents/core/protocol.py
vagents/core/tool.py
vagents/core/vdb.py
vagents/core/wrappers.py
vagents/entrypoint/__init__.py
vagents/entrypoint/main.py
vagents/entrypoint/package_cli.py
vagents/entrypoint/package_manager.py
vagents/entrypoint/vibe.py
vagents/manager/__init__.py
vagents/manager/package.py
vagents/utils/__init__.py
vagents/utils/chat.py
vagents/utils/modality.py
vagents/utils/ui.py
v_agents-0.1.10.dist-info/METADATA
v_agents-0.1.10.dist-info/WHEEL
v_agents-0.1.10.dist-info/entry_points.txt
v_agents-0.1.10.dist-info/top_level.txt
v_agents-0.1.10.dist-info/RECORD
