Metadata-Version: 2.4
Name: v-agents
Version: 0.1.10
Summary: A framework for building scalable and efficient multi-tenant agentic AI systems.
Author-email: Xiaozhe Yao <askxzyao@gmail.com>
Requires-Dist: loguru
Requires-Dist: pydantic
Requires-Dist: aiohttp
Requires-Dist: langfuse
Requires-Dist: diskcache
Requires-Dist: cloudpickle
Requires-Dist: networkx
Requires-Dist: pydot
Requires-Dist: typer
Requires-Dist: fastapi
Requires-Dist: pyzmq
Requires-Dist: psutil
Requires-Dist: uuid7
Requires-Dist: langfuse
Requires-Dist: anyio
Requires-Dist: backoff
Requires-Dist: prompt_toolkit
Requires-Dist: rich
Requires-Dist: jsonref
Requires-Dist: docker
Requires-Dist: tqdm
Requires-Dist: mcp
Requires-Dist: fastmcp
Requires-Dist: dill
Requires-Dist: pillow
Provides-Extra: extra
Requires-Dist: markdownify; extra == "extra"
Requires-Dist: uvenv; extra == "extra"
Requires-Dist: mcp; extra == "extra"
Requires-Dist: fastmcp; extra == "extra"
Provides-Extra: dev
Requires-Dist: black; extra == "dev"
Requires-Dist: pytest; extra == "dev"
Requires-Dist: pre-commit; extra == "dev"
Requires-Dist: pytest-cov; extra == "dev"
Requires-Dist: coverage; extra == "dev"
Requires-Dist: pytest-asyncio; extra == "dev"
Requires-Dist: dstool; extra == "dev"
Requires-Dist: seaborn; extra == "dev"
Requires-Dist: pyrefly; extra == "dev"
Requires-Dist: build; extra == "dev"
Requires-Dist: twine; extra == "dev"
Provides-Extra: all
Requires-Dist: black; extra == "all"
Requires-Dist: pytest; extra == "all"
Requires-Dist: pre-commit; extra == "all"
Requires-Dist: pytest-cov; extra == "all"
Requires-Dist: coverage; extra == "all"
Requires-Dist: pytest-asyncio; extra == "all"
Requires-Dist: dstool; extra == "all"
Requires-Dist: seaborn; extra == "all"
Requires-Dist: pyrefly; extra == "all"
Requires-Dist: build; extra == "all"
Requires-Dist: twine; extra == "all"
Requires-Dist: markdownify; extra == "all"
Requires-Dist: uvenv; extra == "all"
Requires-Dist: mcp; extra == "all"
Requires-Dist: fastmcp; extra == "all"
Requires-Dist: loguru; extra == "all"
Requires-Dist: pydantic; extra == "all"
Requires-Dist: aiohttp; extra == "all"
Requires-Dist: langfuse; extra == "all"
Requires-Dist: diskcache; extra == "all"
Requires-Dist: cloudpickle; extra == "all"
Requires-Dist: networkx; extra == "all"
Requires-Dist: pydot; extra == "all"
Requires-Dist: typer; extra == "all"
Requires-Dist: fastapi; extra == "all"
Requires-Dist: pyzmq; extra == "all"
Requires-Dist: psutil; extra == "all"
Requires-Dist: uuid7; extra == "all"
Requires-Dist: langfuse; extra == "all"
Requires-Dist: anyio; extra == "all"
Requires-Dist: backoff; extra == "all"
Requires-Dist: prompt_toolkit; extra == "all"
Requires-Dist: rich; extra == "all"
Requires-Dist: jsonref; extra == "all"
Requires-Dist: docker; extra == "all"
Requires-Dist: tqdm; extra == "all"
Requires-Dist: mcp; extra == "all"
Requires-Dist: fastmcp; extra == "all"
Requires-Dist: dill; extra == "all"
Requires-Dist: pillow; extra == "all"
